huggingface_rdf/__init__.py
huggingface_rdf/fetch_data.py
huggingface_rdf/generate_rdf.py
kaggle_rdf/__init__.py
kaggle_rdf/fetch_data.py
kaggle_rdf/generate_rdf.py
huggingface_rdf-0.1.0.dist-info/LICENSE
huggingface_rdf-0.1.0.dist-info/METADATA
huggingface_rdf-0.1.0.dist-info/WHEEL
huggingface_rdf-0.1.0.dist-info/entry_points.txt
huggingface_rdf-0.1.0.dist-info/top_level.txt
huggingface_rdf-0.1.0.dist-info/RECORD
