Metadata-Version: 2.1
Name: huggingface-rdf
Version: 0.1.0
Summary: A command-line tool for generating UMAP plots and KMeans clustering from JSONL data
Home-page: https://github.com/david4096/huggingface-rdf
Author: David Steinberg
Author-email: david@resium.com
Classifier: Programming Language :: Python :: 3
Classifier: License :: OSI Approved :: MIT License
Classifier: Operating System :: OS Independent
Requires-Python: >=3.8
License-File: LICENSE
Requires-Dist: huggingface-hub
Requires-Dist: rdflib
Requires-Dist: qlever
Requires-Dist: kaggle
